<?xml version='1.0' encoding='UTF-8'?>
<?artifactRepository version='1.1.0'?>
<repository name='file:/home/runner/work/spotbugs/spotbugs/eclipsePlugin/build/site/eclipse-daily/ - artifacts' type='org.eclipse.equinox.p2.artifact.repository.simpleRepository' version='1'>
  <properties size='2'>
    <property name='p2.timestamp' value='1632383957120'/>
    <property name='p2.compressed' value='false'/>
  </properties>
  <mappings size='3'>
    <rule filter='(&amp; (classifier=osgi.bundle))' output='${repoUrl}/plugins/${id}_${version}.jar'/>
    <rule filter='(&amp; (classifier=binary))' output='${repoUrl}/binary/${id}_${version}'/>
    <rule filter='(&amp; (classifier=org.eclipse.update.feature))' output='${repoUrl}/features/${id}_${version}.jar'/>
  </mappings>
  <artifacts size='2'>
    <artifact classifier='org.eclipse.update.feature' id='com.github.spotbugs.plugin.eclipse' version='4.4.2.202109230758-c35d650'>
      <properties size='4'>
        <property name='artifact.size' value='7777'/>
        <property name='download.size' value='7777'/>
        <property name='download.md5' value='a829f643c9187949a5d90327f39956cc'/>
        <property name='download.contentType' value='application/zip'/>
      </properties>
    </artifact>
    <artifact classifier='osgi.bundle' id='com.github.spotbugs.plugin.eclipse' version='4.4.2.202109230758-c35d650'>
      <properties size='3'>
        <property name='artifact.size' value='10414507'/>
        <property name='download.size' value='10414507'/>
        <property name='download.md5' value='ef15af367967bbea5dc2df07738dd725'/>
      </properties>
    </artifact>
  </artifacts>
</repository>
