<?xml version='1.0' encoding='UTF-8'?>
<?artifactRepository version='1.1.0'?>
<repository name='file:/home/runner/work/spotbugs/spotbugs/eclipsePlugin/build/site/eclipse-daily/ - artifacts' type='org.eclipse.equinox.p2.artifact.repository.simpleRepository' version='1'>
  <properties size='2'>
    <property name='p2.timestamp' value='1712787772734'/>
    <property name='p2.compressed' value='false'/>
  </properties>
  <mappings size='3'>
    <rule filter='(&amp; (classifier=osgi.bundle))' output='${repoUrl}/plugins/${id}_${version}.jar'/>
    <rule filter='(&amp; (classifier=binary))' output='${repoUrl}/binary/${id}_${version}'/>
    <rule filter='(&amp; (classifier=org.eclipse.update.feature))' output='${repoUrl}/features/${id}_${version}.jar'/>
  </mappings>
  <artifacts size='2'>
    <artifact classifier='osgi.bundle' id='com.github.spotbugs.plugin.eclipse' version='4.8.5.202404102221-bb90040'>
      <properties size='5'>
        <property name='artifact.size' value='11964188'/>
        <property name='download.size' value='11964188'/>
        <property name='download.md5' value='2c2b1be41954d99817323be99ef2dedb'/>
        <property name='download.checksum.md5' value='2c2b1be41954d99817323be99ef2dedb'/>
        <property name='download.checksum.sha-256' value='1ba4261927c6d909e82b523d396af0020e7b04ee02d23732582e8b4788333e75'/>
      </properties>
    </artifact>
    <artifact classifier='org.eclipse.update.feature' id='com.github.spotbugs.plugin.eclipse' version='4.8.5.202404102221-bb90040'>
      <properties size='6'>
        <property name='artifact.size' value='11310'/>
        <property name='download.size' value='11310'/>
        <property name='download.md5' value='d3475b2b8d9dea673d0e8c2eaa3b5c0a'/>
        <property name='download.checksum.md5' value='d3475b2b8d9dea673d0e8c2eaa3b5c0a'/>
        <property name='download.checksum.sha-256' value='181c82637b80fe1e6c95e978c1fb488175588ac5b5921f2843c11f07717a0457'/>
        <property name='download.contentType' value='application/zip'/>
      </properties>
    </artifact>
  </artifacts>
</repository>
