<?xml version='1.0' encoding='UTF-8'?>
<?artifactRepository version='1.1.0'?>
<repository name='file:/home/runner/work/spotbugs/spotbugs/eclipsePlugin/build/site/eclipse-daily/ - artifacts' type='org.eclipse.equinox.p2.artifact.repository.simpleRepository' version='1'>
  <properties size='2'>
    <property name='p2.timestamp' value='1701167842349'/>
    <property name='p2.compressed' value='false'/>
  </properties>
  <mappings size='3'>
    <rule filter='(&amp; (classifier=osgi.bundle))' output='${repoUrl}/plugins/${id}_${version}.jar'/>
    <rule filter='(&amp; (classifier=binary))' output='${repoUrl}/binary/${id}_${version}'/>
    <rule filter='(&amp; (classifier=org.eclipse.update.feature))' output='${repoUrl}/features/${id}_${version}.jar'/>
  </mappings>
  <artifacts size='2'>
    <artifact classifier='osgi.bundle' id='com.github.spotbugs.plugin.eclipse' version='4.8.2.202311281036-e847d62'>
      <properties size='4'>
        <property name='artifact.size' value='11880018'/>
        <property name='download.size' value='11880018'/>
        <property name='download.checksum.sha-512' value='5bfebb3e3849ec42e01266ae8e2fd97ee5f0e3f2b0b10039a3ffa27f3daa7f42c691259642136f227e197d159b4ed6a96496b0db8665716a507ed184a8a4e7ca'/>
        <property name='download.checksum.sha-256' value='17c50cef5a3093d05aefacd695f461e0276f5f908e9aecfa5425bee02ba4876f'/>
      </properties>
    </artifact>
    <artifact classifier='org.eclipse.update.feature' id='com.github.spotbugs.plugin.eclipse' version='4.8.2.202311281036-e847d62'>
      <properties size='5'>
        <property name='artifact.size' value='11316'/>
        <property name='download.size' value='11316'/>
        <property name='download.checksum.sha-512' value='5d6ce16bf6791e6186870d821a226aa364466cf0a5b2c7d600bead0f3413a81aa80679d43d53b8f3b7ecd0b713aec77d874bb4debfbb0e4ff294d5d989aaa39b'/>
        <property name='download.checksum.sha-256' value='3e2821394095cbe72a27354e3644bd3f68e3ee4f7c8153e7a8815752342b5e55'/>
        <property name='download.contentType' value='application/zip'/>
      </properties>
    </artifact>
  </artifacts>
</repository>
